meteoroscanner/Coordinfo.py
meteoroscanner/__init__.py
meteoroscanner/colorbar.py
meteoroscanner/meteoroscanner.py
meteoroscanner-0.1.1.dist-info/METADATA
meteoroscanner-0.1.1.dist-info/WHEEL
meteoroscanner-0.1.1.dist-info/top_level.txt
meteoroscanner-0.1.1.dist-info/RECORD
