Metadata-Version: 2.2
Name: meteoroscanner
Version: 0.1.1
Summary: A module used for making continuous cross-section view of the atmosphere.
Author: Wend3620
License: GPLv3
Classifier: License :: OSI Approved :: GNU General Public License v3 (GPLv3)
Classifier: Intended Audience :: Science/Research
Requires-Python: >=3.10
Requires-Dist: metpy
Requires-Dist: cartopy
Requires-Dist: matplotlib
Requires-Dist: xarray
Requires-Dist: numpy
Requires-Dist: scipy
Dynamic: author
Dynamic: classifier
Dynamic: description
Dynamic: description-content-type
Dynamic: license
Dynamic: requires-dist
Dynamic: requires-python
Dynamic: summary
